{
  "annotations": {
    "list": [
      {
        "builtIn": 1,
        "datasource": "-- Grafana --",
        "enable": true,
        "hide": true,
        "iconColor": "rgba(0, 211, 255, 1)",
        "name": "Annotations & Alerts",
        "type": "dashboard"
      }
    ]
  },
  "editable": true,
  "gnetId": null,
  "graphTooltip": 0,
  "id": 2,
  "iteration": 1553908362579,
  "links": [],
  "panels": [
    {
      "datasource": "Gradients2",
      "fill": 0,
      "gridPos": {
        "h": 8,
        "w": 7,
        "x": 0,
        "y": 0
      },
      "id": 14,
      "lines": false,
      "linewidth": 1,
      "links": [],
      "pointradius": 1,
      "points": true,
      "range": {
        "from": null,
        "to": null
      },
      "targets": [
        {
          "format": "time_series",
          "group": [
            {
              "params": [
                "$__interval",
                "none"
              ],
              "type": "time"
            }
          ],
          "metricColumn": "none",
          "rawQuery": false,
          "rawSql": "SELECT\n  $__timeGroupAlias(\"time\",$__interval),\n  avg(lat) AS \"lat\"\nFROM tsgraw_geo\nWHERE\n  $__timeFilter(\"time\")\nGROUP BY 1\nORDER BY 1",
          "refId": "A",
          "select": [
            [
              {
                "params": [
                  "lat"
                ],
                "type": "column"
              },
              {
                "params": [
                  "avg"
                ],
                "type": "aggregate"
              },
              {
                "params": [
                  "lat"
                ],
                "type": "alias"
              }
            ]
          ],
          "table": "tsgraw_geo",
          "timeColumn": "\"time\"",
          "timeColumnType": "timestamptz",
          "where": [
            {
              "name": "$__timeFilter",
              "params": [],
              "type": "macro"
            }
          ]
        },
        {
          "format": "time_series",
          "group": [
            {
              "params": [
                "$__interval",
                "none"
              ],
              "type": "time"
            }
          ],
          "metricColumn": "none",
          "rawQuery": false,
          "rawSql": "SELECT\n  $__timeGroupAlias(\"time\",$__interval),\n  avg(temp2) AS \"temp N\"\nFROM tsgraw_geo\nWHERE\n  $__timeFilter(\"time\") AND\n  \"time\" <= '$turnaround'\nGROUP BY 1\nORDER BY 1",
          "refId": "C",
          "select": [
            [
              {
                "params": [
                  "temp2"
                ],
                "type": "column"
              },
              {
                "params": [
                  "avg"
                ],
                "type": "aggregate"
              },
              {
                "params": [
                  "temp N"
                ],
                "type": "alias"
              }
            ]
          ],
          "table": "tsgraw_geo",
          "timeColumn": "\"time\"",
          "timeColumnType": "timestamptz",
          "where": [
            {
              "name": "$__timeFilter",
              "params": [],
              "type": "macro"
            },
            {
              "datatype": "timestamptz",
              "name": "",
              "params": [
                "\"time\"",
                "<=",
                "'$turnaround'"
              ],
              "type": "expression"
            }
          ]
        },
        {
          "format": "time_series",
          "group": [
            {
              "params": [
                "$__interval",
                "none"
              ],
              "type": "time"
            }
          ],
          "metricColumn": "none",
          "rawQuery": false,
          "rawSql": "SELECT\n  $__timeGroupAlias(\"time\",$__interval),\n  avg(temp2) AS \"temp S\"\nFROM tsgraw_geo\nWHERE\n  $__timeFilter(\"time\") AND\n  \"time\" >= '$turnaround'\nGROUP BY 1\nORDER BY 1",
          "refId": "B",
          "select": [
            [
              {
                "params": [
                  "temp2"
                ],
                "type": "column"
              },
              {
                "params": [
                  "avg"
                ],
                "type": "aggregate"
              },
              {
                "params": [
                  "temp S"
                ],
                "type": "alias"
              }
            ]
          ],
          "table": "tsgraw_geo",
          "timeColumn": "\"time\"",
          "timeColumnType": "timestamptz",
          "where": [
            {
              "name": "$__timeFilter",
              "params": [],
              "type": "macro"
            },
            {
              "datatype": "timestamptz",
              "name": "",
              "params": [
                "\"time\"",
                ">=",
                "'$turnaround'"
              ],
              "type": "expression"
            }
          ]
        }
      ],
      "timeFrom": null,
      "timeShift": null,
      "title": "Temperature",
      "type": "armbrustlab-2dscatter-panel",
      "xaxis": {
        "show": true
      },
      "yaxes": [
        {
          "format": "short",
          "logBase": 1,
          "show": true
        }
      ]
    },
    {
      "datasource": "Gradients2",
      "fill": 0,
      "gridPos": {
        "h": 8,
        "w": 7,
        "x": 7,
        "y": 0
      },
      "id": 16,
      "lines": false,
      "linewidth": 1,
      "links": [],
      "pointradius": 1,
      "points": true,
      "range": {
        "from": null,
        "to": null
      },
      "targets": [
        {
          "format": "time_series",
          "group": [
            {
              "params": [
                "$__interval",
                "none"
              ],
              "type": "time"
            }
          ],
          "metricColumn": "none",
          "rawQuery": false,
          "rawSql": "SELECT\n  $__timeGroupAlias(\"time\",$__interval),\n  avg(lat) AS \"lat\"\nFROM tsgraw_geo\nWHERE\n  $__timeFilter(\"time\")\nGROUP BY 1\nORDER BY 1",
          "refId": "A",
          "select": [
            [
              {
                "params": [
                  "lat"
                ],
                "type": "column"
              },
              {
                "params": [
                  "avg"
                ],
                "type": "aggregate"
              },
              {
                "params": [
                  "lat"
                ],
                "type": "alias"
              }
            ]
          ],
          "table": "tsgraw_geo",
          "timeColumn": "\"time\"",
          "timeColumnType": "timestamptz",
          "where": [
            {
              "name": "$__timeFilter",
              "params": [],
              "type": "macro"
            }
          ]
        },
        {
          "format": "time_series",
          "group": [
            {
              "params": [
                "$__interval",
                "none"
              ],
              "type": "time"
            }
          ],
          "metricColumn": "none",
          "rawQuery": false,
          "rawSql": "SELECT\n  $__timeGroupAlias(\"time\",$__interval),\n  avg(salinity) AS \"salinity N\"\nFROM tsgraw_geo\nWHERE\n  $__timeFilter(\"time\") AND\n  \"time\" <= '$turnaround'\nGROUP BY 1\nORDER BY 1",
          "refId": "B",
          "select": [
            [
              {
                "params": [
                  "salinity"
                ],
                "type": "column"
              },
              {
                "params": [
                  "avg"
                ],
                "type": "aggregate"
              },
              {
                "params": [
                  "salinity N"
                ],
                "type": "alias"
              }
            ]
          ],
          "table": "tsgraw_geo",
          "timeColumn": "\"time\"",
          "timeColumnType": "timestamptz",
          "where": [
            {
              "name": "$__timeFilter",
              "params": [],
              "type": "macro"
            },
            {
              "datatype": "timestamptz",
              "name": "",
              "params": [
                "\"time\"",
                "<=",
                "'$turnaround'"
              ],
              "type": "expression"
            }
          ]
        },
        {
          "format": "time_series",
          "group": [
            {
              "params": [
                "$__interval",
                "none"
              ],
              "type": "time"
            }
          ],
          "metricColumn": "none",
          "rawQuery": false,
          "rawSql": "SELECT\n  $__timeGroupAlias(\"time\",$__interval),\n  avg(salinity) AS \"salinity S\"\nFROM tsgraw_geo\nWHERE\n  $__timeFilter(\"time\") AND\n  \"time\" >= '$turnaround'\nGROUP BY 1\nORDER BY 1",
          "refId": "C",
          "select": [
            [
              {
                "params": [
                  "salinity"
                ],
                "type": "column"
              },
              {
                "params": [
                  "avg"
                ],
                "type": "aggregate"
              },
              {
                "params": [
                  "salinity S"
                ],
                "type": "alias"
              }
            ]
          ],
          "table": "tsgraw_geo",
          "timeColumn": "\"time\"",
          "timeColumnType": "timestamptz",
          "where": [
            {
              "name": "$__timeFilter",
              "params": [],
              "type": "macro"
            },
            {
              "datatype": "timestamptz",
              "name": "",
              "params": [
                "\"time\"",
                ">=",
                "'$turnaround'"
              ],
              "type": "expression"
            }
          ]
        }
      ],
      "timeFrom": null,
      "timeShift": null,
      "title": "Salinity",
      "type": "armbrustlab-2dscatter-panel",
      "xaxis": {
        "show": true
      },
      "yaxes": [
        {
          "format": "short",
          "logBase": 1,
          "min": null,
          "show": true
        }
      ]
    },
    {
      "datasource": "Gradients2",
      "fill": 1,
      "gridPos": {
        "h": 8,
        "w": 6,
        "x": 14,
        "y": 0
      },
      "id": 12,
      "lines": true,
      "linewidth": 1,
      "links": [],
      "pointradius": 1,
      "points": true,
      "range": {
        "from": null,
        "to": null
      },
      "targets": [
        {
          "format": "time_series",
          "group": [
            {
              "params": [
                "$__interval",
                "none"
              ],
              "type": "time"
            }
          ],
          "metricColumn": "none",
          "rawQuery": false,
          "rawSql": "SELECT\n  $__timeGroupAlias(\"time\",$__interval),\n  avg(lat) AS \"lat\"\nFROM par_geo\nWHERE\n  $__timeFilter(\"time\")\nGROUP BY 1\nORDER BY 1",
          "refId": "A",
          "select": [
            [
              {
                "params": [
                  "lat"
                ],
                "type": "column"
              },
              {
                "params": [
                  "avg"
                ],
                "type": "aggregate"
              },
              {
                "params": [
                  "lat"
                ],
                "type": "alias"
              }
            ]
          ],
          "table": "par_geo",
          "timeColumn": "\"time\"",
          "timeColumnType": "timestamptz",
          "where": [
            {
              "name": "$__timeFilter",
              "params": [],
              "type": "macro"
            }
          ]
        },
        {
          "format": "time_series",
          "group": [
            {
              "params": [
                "$__interval",
                "none"
              ],
              "type": "time"
            }
          ],
          "metricColumn": "none",
          "rawQuery": false,
          "rawSql": "SELECT\n  $__timeGroupAlias(\"time\",$__interval),\n  avg(par) AS \"par N\"\nFROM par_geo\nWHERE\n  $__timeFilter(\"time\") AND\n  \"time\" >= '$turnaround'\nGROUP BY 1\nORDER BY 1",
          "refId": "B",
          "select": [
            [
              {
                "params": [
                  "par"
                ],
                "type": "column"
              },
              {
                "params": [
                  "avg"
                ],
                "type": "aggregate"
              },
              {
                "params": [
                  "par N"
                ],
                "type": "alias"
              }
            ]
          ],
          "table": "par_geo",
          "timeColumn": "\"time\"",
          "timeColumnType": "timestamptz",
          "where": [
            {
              "name": "$__timeFilter",
              "params": [],
              "type": "macro"
            },
            {
              "datatype": "timestamptz",
              "name": "",
              "params": [
                "\"time\"",
                ">=",
                "'$turnaround'"
              ],
              "type": "expression"
            }
          ]
        },
        {
          "format": "time_series",
          "group": [
            {
              "params": [
                "$__interval",
                "none"
              ],
              "type": "time"
            }
          ],
          "metricColumn": "none",
          "rawQuery": false,
          "rawSql": "SELECT\n  $__timeGroupAlias(\"time\",$__interval),\n  avg(par) AS \"par S\"\nFROM par_geo\nWHERE\n  $__timeFilter(\"time\") AND\n  \"time\" <= '$turnaround'\nGROUP BY 1\nORDER BY 1",
          "refId": "C",
          "select": [
            [
              {
                "params": [
                  "par"
                ],
                "type": "column"
              },
              {
                "params": [
                  "avg"
                ],
                "type": "aggregate"
              },
              {
                "params": [
                  "par S"
                ],
                "type": "alias"
              }
            ]
          ],
          "table": "par_geo",
          "timeColumn": "\"time\"",
          "timeColumnType": "timestamptz",
          "where": [
            {
              "name": "$__timeFilter",
              "params": [],
              "type": "macro"
            },
            {
              "datatype": "timestamptz",
              "name": "",
              "params": [
                "\"time\"",
                "<=",
                "'$turnaround'"
              ],
              "type": "expression"
            }
          ]
        }
      ],
      "timeFrom": null,
      "timeShift": null,
      "title": "PAR",
      "type": "armbrustlab-2dscatter-panel",
      "xaxis": {
        "show": true
      },
      "yaxes": [
        {
          "format": "short",
          "logBase": 1,
          "show": true
        }
      ]
    },
    {
      "datasource": "Gradients2",
      "fill": 0,
      "gridPos": {
        "h": 8,
        "w": 10,
        "x": 0,
        "y": 8
      },
      "id": 10,
      "lines": false,
      "linewidth": 1,
      "links": [],
      "pointradius": 1,
      "points": true,
      "range": {
        "from": null,
        "to": null
      },
      "targets": [
        {
          "format": "time_series",
          "group": [
            {
              "params": [
                "$__interval",
                "none"
              ],
              "type": "time"
            }
          ],
          "metricColumn": "none",
          "rawQuery": false,
          "rawSql": "SELECT\n  $__timeGroupAlias(\"time\",$__interval),\n  avg(lat) AS \"lat\"\nFROM seaflow_geo\nWHERE\n  $__timeFilter(\"time\") AND\n  pop = 'prochloro'\nGROUP BY 1\nORDER BY 1",
          "refId": "A",
          "select": [
            [
              {
                "params": [
                  "lat"
                ],
                "type": "column"
              },
              {
                "params": [
                  "avg"
                ],
                "type": "aggregate"
              },
              {
                "params": [
                  "lat"
                ],
                "type": "alias"
              }
            ]
          ],
          "table": "seaflow_geo",
          "timeColumn": "\"time\"",
          "timeColumnType": "timestamptz",
          "where": [
            {
              "name": "$__timeFilter",
              "params": [],
              "type": "macro"
            },
            {
              "datatype": "text",
              "name": "",
              "params": [
                "pop",
                "=",
                "'prochloro'"
              ],
              "type": "expression"
            }
          ]
        },
        {
          "format": "time_series",
          "group": [
            {
              "params": [
                "$__interval",
                "none"
              ],
              "type": "time"
            }
          ],
          "metricColumn": "none",
          "rawQuery": false,
          "rawSql": "SELECT\n  $__timeGroupAlias(\"time\",$__interval),\n  avg(abundance) AS \"pro N\"\nFROM seaflow_geo\nWHERE\n  $__timeFilter(\"time\") AND\n  pop = 'prochloro' AND\n  \"time\" <= '$turnaround'\nGROUP BY 1\nORDER BY 1",
          "refId": "B",
          "select": [
            [
              {
                "params": [
                  "abundance"
                ],
                "type": "column"
              },
              {
                "params": [
                  "avg"
                ],
                "type": "aggregate"
              },
              {
                "params": [
                  "pro N"
                ],
                "type": "alias"
              }
            ]
          ],
          "table": "seaflow_geo",
          "timeColumn": "\"time\"",
          "timeColumnType": "timestamptz",
          "where": [
            {
              "name": "$__timeFilter",
              "params": [],
              "type": "macro"
            },
            {
              "datatype": "text",
              "name": "",
              "params": [
                "pop",
                "=",
                "'prochloro'"
              ],
              "type": "expression"
            },
            {
              "datatype": "timestamptz",
              "name": "",
              "params": [
                "\"time\"",
                "<=",
                "'$turnaround'"
              ],
              "type": "expression"
            }
          ]
        },
        {
          "format": "time_series",
          "group": [
            {
              "params": [
                "$__interval",
                "none"
              ],
              "type": "time"
            }
          ],
          "metricColumn": "none",
          "rawQuery": false,
          "rawSql": "SELECT\n  $__timeGroupAlias(\"time\",$__interval),\n  avg(abundance) AS \"pro S\"\nFROM seaflow_geo\nWHERE\n  $__timeFilter(\"time\") AND\n  pop = 'prochloro' AND\n  \"time\" >= '$turnaround'\nGROUP BY 1\nORDER BY 1",
          "refId": "C",
          "select": [
            [
              {
                "params": [
                  "abundance"
                ],
                "type": "column"
              },
              {
                "params": [
                  "avg"
                ],
                "type": "aggregate"
              },
              {
                "params": [
                  "pro S"
                ],
                "type": "alias"
              }
            ]
          ],
          "table": "seaflow_geo",
          "timeColumn": "\"time\"",
          "timeColumnType": "timestamptz",
          "where": [
            {
              "name": "$__timeFilter",
              "params": [],
              "type": "macro"
            },
            {
              "datatype": "text",
              "name": "",
              "params": [
                "pop",
                "=",
                "'prochloro'"
              ],
              "type": "expression"
            },
            {
              "datatype": "timestamptz",
              "name": "",
              "params": [
                "\"time\"",
                ">=",
                "'$turnaround'"
              ],
              "type": "expression"
            }
          ]
        }
      ],
      "timeFrom": null,
      "timeShift": null,
      "title": "Prochlorococcus Abundance",
      "type": "armbrustlab-2dscatter-panel",
      "xaxis": {
        "show": true
      },
      "yaxes": [
        {
          "format": "short",
          "logBase": 1,
          "max": "300",
          "show": true
        }
      ]
    },
    {
      "datasource": "Gradients2",
      "fill": 0,
      "gridPos": {
        "h": 8,
        "w": 10,
        "x": 10,
        "y": 8
      },
      "id": 18,
      "lines": false,
      "linewidth": 1,
      "links": [],
      "pointradius": 1,
      "points": true,
      "range": {
        "from": null,
        "to": null
      },
      "targets": [
        {
          "format": "time_series",
          "group": [
            {
              "params": [
                "$__interval",
                "none"
              ],
              "type": "time"
            }
          ],
          "metricColumn": "none",
          "rawQuery": false,
          "rawSql": "SELECT\n  $__timeGroupAlias(\"time\",$__interval),\n  avg(lat) AS \"lat\"\nFROM seaflow_geo\nWHERE\n  $__timeFilter(\"time\")\nGROUP BY 1\nORDER BY 1",
          "refId": "A",
          "select": [
            [
              {
                "params": [
                  "lat"
                ],
                "type": "column"
              },
              {
                "params": [
                  "avg"
                ],
                "type": "aggregate"
              },
              {
                "params": [
                  "lat"
                ],
                "type": "alias"
              }
            ]
          ],
          "table": "seaflow_geo",
          "timeColumn": "\"time\"",
          "timeColumnType": "timestamptz",
          "where": [
            {
              "name": "$__timeFilter",
              "params": [],
              "type": "macro"
            }
          ]
        },
        {
          "format": "time_series",
          "group": [
            {
              "params": [
                "$__interval",
                "none"
              ],
              "type": "time"
            }
          ],
          "metricColumn": "none",
          "rawQuery": false,
          "rawSql": "SELECT\n  $__timeGroupAlias(\"time\",$__interval),\n  avg(fsc_small) AS \"pro N\"\nFROM seaflow_geo\nWHERE\n  $__timeFilter(\"time\") AND\n  pop = 'prochloro' AND\n  \"time\" <= '$turnaround'\nGROUP BY 1\nORDER BY 1",
          "refId": "B",
          "select": [
            [
              {
                "params": [
                  "fsc_small"
                ],
                "type": "column"
              },
              {
                "params": [
                  "avg"
                ],
                "type": "aggregate"
              },
              {
                "params": [
                  "pro N"
                ],
                "type": "alias"
              }
            ]
          ],
          "table": "seaflow_geo",
          "timeColumn": "\"time\"",
          "timeColumnType": "timestamptz",
          "where": [
            {
              "name": "$__timeFilter",
              "params": [],
              "type": "macro"
            },
            {
              "datatype": "text",
              "name": "",
              "params": [
                "pop",
                "=",
                "'prochloro'"
              ],
              "type": "expression"
            },
            {
              "datatype": "timestamptz",
              "name": "",
              "params": [
                "\"time\"",
                "<=",
                "'$turnaround'"
              ],
              "type": "expression"
            }
          ]
        },
        {
          "format": "time_series",
          "group": [
            {
              "params": [
                "$__interval",
                "none"
              ],
              "type": "time"
            }
          ],
          "metricColumn": "none",
          "rawQuery": false,
          "rawSql": "SELECT\n  $__timeGroupAlias(\"time\",$__interval),\n  avg(fsc_small) AS \"pro S\"\nFROM seaflow_geo\nWHERE\n  $__timeFilter(\"time\") AND\n  pop = 'prochloro' AND\n  \"time\" >= '$turnaround'\nGROUP BY 1\nORDER BY 1",
          "refId": "C",
          "select": [
            [
              {
                "params": [
                  "fsc_small"
                ],
                "type": "column"
              },
              {
                "params": [
                  "avg"
                ],
                "type": "aggregate"
              },
              {
                "params": [
                  "pro S"
                ],
                "type": "alias"
              }
            ]
          ],
          "table": "seaflow_geo",
          "timeColumn": "\"time\"",
          "timeColumnType": "timestamptz",
          "where": [
            {
              "name": "$__timeFilter",
              "params": [],
              "type": "macro"
            },
            {
              "datatype": "text",
              "name": "",
              "params": [
                "pop",
                "=",
                "'prochloro'"
              ],
              "type": "expression"
            },
            {
              "datatype": "timestamptz",
              "name": "",
              "params": [
                "\"time\"",
                ">=",
                "'$turnaround'"
              ],
              "type": "expression"
            }
          ]
        }
      ],
      "timeFrom": null,
      "timeShift": null,
      "title": "Prochlorococcus Forward Scatter",
      "type": "armbrustlab-2dscatter-panel",
      "xaxis": {
        "show": true
      },
      "yaxes": [
        {
          "format": "short",
          "logBase": 1,
          "show": true
        }
      ]
    },
    {
      "datasource": "Gradients2",
      "fill": 0,
      "gridPos": {
        "h": 8,
        "w": 10,
        "x": 0,
        "y": 16
      },
      "id": 32,
      "lines": false,
      "linewidth": 1,
      "links": [],
      "pointradius": 1,
      "points": true,
      "range": {
        "from": null,
        "to": null
      },
      "targets": [
        {
          "format": "time_series",
          "group": [
            {
              "params": [
                "$__interval",
                "none"
              ],
              "type": "time"
            }
          ],
          "metricColumn": "none",
          "rawQuery": false,
          "rawSql": "SELECT\n  $__timeGroupAlias(\"time\",$__interval),\n  avg(lat) AS \"lat\"\nFROM seaflow_geo\nWHERE\n  $__timeFilter(\"time\") AND\n  pop = 'synecho'\nGROUP BY 1\nORDER BY 1",
          "refId": "A",
          "select": [
            [
              {
                "params": [
                  "lat"
                ],
                "type": "column"
              },
              {
                "params": [
                  "avg"
                ],
                "type": "aggregate"
              },
              {
                "params": [
                  "lat"
                ],
                "type": "alias"
              }
            ]
          ],
          "table": "seaflow_geo",
          "timeColumn": "\"time\"",
          "timeColumnType": "timestamptz",
          "where": [
            {
              "name": "$__timeFilter",
              "params": [],
              "type": "macro"
            },
            {
              "datatype": "text",
              "name": "",
              "params": [
                "pop",
                "=",
                "'synecho'"
              ],
              "type": "expression"
            }
          ]
        },
        {
          "format": "time_series",
          "group": [
            {
              "params": [
                "$__interval",
                "none"
              ],
              "type": "time"
            }
          ],
          "metricColumn": "none",
          "rawQuery": false,
          "rawSql": "SELECT\n  $__timeGroupAlias(\"time\",$__interval),\n  avg(abundance) AS \"pro N\"\nFROM seaflow_geo\nWHERE\n  $__timeFilter(\"time\") AND\n  pop = 'synecho' AND\n  \"time\" <= '$turnaround'\nGROUP BY 1\nORDER BY 1",
          "refId": "B",
          "select": [
            [
              {
                "params": [
                  "abundance"
                ],
                "type": "column"
              },
              {
                "params": [
                  "avg"
                ],
                "type": "aggregate"
              },
              {
                "params": [
                  "pro N"
                ],
                "type": "alias"
              }
            ]
          ],
          "table": "seaflow_geo",
          "timeColumn": "\"time\"",
          "timeColumnType": "timestamptz",
          "where": [
            {
              "name": "$__timeFilter",
              "params": [],
              "type": "macro"
            },
            {
              "datatype": "text",
              "name": "",
              "params": [
                "pop",
                "=",
                "'synecho'"
              ],
              "type": "expression"
            },
            {
              "datatype": "timestamptz",
              "name": "",
              "params": [
                "\"time\"",
                "<=",
                "'$turnaround'"
              ],
              "type": "expression"
            }
          ]
        },
        {
          "format": "time_series",
          "group": [
            {
              "params": [
                "$__interval",
                "none"
              ],
              "type": "time"
            }
          ],
          "metricColumn": "none",
          "rawQuery": false,
          "rawSql": "SELECT\n  $__timeGroupAlias(\"time\",$__interval),\n  avg(abundance) AS \"pro S\"\nFROM seaflow_geo\nWHERE\n  $__timeFilter(\"time\") AND\n  pop = 'synecho' AND\n  \"time\" >= '$turnaround'\nGROUP BY 1\nORDER BY 1",
          "refId": "C",
          "select": [
            [
              {
                "params": [
                  "abundance"
                ],
                "type": "column"
              },
              {
                "params": [
                  "avg"
                ],
                "type": "aggregate"
              },
              {
                "params": [
                  "pro S"
                ],
                "type": "alias"
              }
            ]
          ],
          "table": "seaflow_geo",
          "timeColumn": "\"time\"",
          "timeColumnType": "timestamptz",
          "where": [
            {
              "name": "$__timeFilter",
              "params": [],
              "type": "macro"
            },
            {
              "datatype": "text",
              "name": "",
              "params": [
                "pop",
                "=",
                "'synecho'"
              ],
              "type": "expression"
            },
            {
              "datatype": "timestamptz",
              "name": "",
              "params": [
                "\"time\"",
                ">=",
                "'$turnaround'"
              ],
              "type": "expression"
            }
          ]
        }
      ],
      "timeFrom": null,
      "timeShift": null,
      "title": "Synechococcus Abundance",
      "type": "armbrustlab-2dscatter-panel",
      "xaxis": {
        "show": true
      },
      "yaxes": [
        {
          "format": "short",
          "logBase": 1,
          "max": null,
          "show": true
        }
      ]
    },
    {
      "datasource": "Gradients2",
      "fill": 0,
      "gridPos": {
        "h": 8,
        "w": 10,
        "x": 10,
        "y": 16
      },
      "id": 34,
      "lines": false,
      "linewidth": 1,
      "links": [],
      "pointradius": 1,
      "points": true,
      "range": {
        "from": null,
        "to": null
      },
      "targets": [
        {
          "format": "time_series",
          "group": [
            {
              "params": [
                "$__interval",
                "none"
              ],
              "type": "time"
            }
          ],
          "metricColumn": "none",
          "rawQuery": false,
          "rawSql": "SELECT\n  $__timeGroupAlias(\"time\",$__interval),\n  avg(lat) AS \"lat\"\nFROM seaflow_geo\nWHERE\n  $__timeFilter(\"time\") AND\n  pop = 'synecho'\nGROUP BY 1\nORDER BY 1",
          "refId": "A",
          "select": [
            [
              {
                "params": [
                  "lat"
                ],
                "type": "column"
              },
              {
                "params": [
                  "avg"
                ],
                "type": "aggregate"
              },
              {
                "params": [
                  "lat"
                ],
                "type": "alias"
              }
            ]
          ],
          "table": "seaflow_geo",
          "timeColumn": "\"time\"",
          "timeColumnType": "timestamptz",
          "where": [
            {
              "name": "$__timeFilter",
              "params": [],
              "type": "macro"
            },
            {
              "datatype": "text",
              "name": "",
              "params": [
                "pop",
                "=",
                "'synecho'"
              ],
              "type": "expression"
            }
          ]
        },
        {
          "format": "time_series",
          "group": [
            {
              "params": [
                "$__interval",
                "none"
              ],
              "type": "time"
            }
          ],
          "metricColumn": "none",
          "rawQuery": false,
          "rawSql": "SELECT\n  $__timeGroupAlias(\"time\",$__interval),\n  avg(fsc_small) AS \"pro N\"\nFROM seaflow_geo\nWHERE\n  $__timeFilter(\"time\") AND\n  pop = 'synecho' AND\n  \"time\" <= '$turnaround'\nGROUP BY 1\nORDER BY 1",
          "refId": "B",
          "select": [
            [
              {
                "params": [
                  "fsc_small"
                ],
                "type": "column"
              },
              {
                "params": [
                  "avg"
                ],
                "type": "aggregate"
              },
              {
                "params": [
                  "pro N"
                ],
                "type": "alias"
              }
            ]
          ],
          "table": "seaflow_geo",
          "timeColumn": "\"time\"",
          "timeColumnType": "timestamptz",
          "where": [
            {
              "name": "$__timeFilter",
              "params": [],
              "type": "macro"
            },
            {
              "datatype": "text",
              "name": "",
              "params": [
                "pop",
                "=",
                "'synecho'"
              ],
              "type": "expression"
            },
            {
              "datatype": "timestamptz",
              "name": "",
              "params": [
                "\"time\"",
                "<=",
                "'$turnaround'"
              ],
              "type": "expression"
            }
          ]
        },
        {
          "format": "time_series",
          "group": [
            {
              "params": [
                "$__interval",
                "none"
              ],
              "type": "time"
            }
          ],
          "metricColumn": "none",
          "rawQuery": false,
          "rawSql": "SELECT\n  $__timeGroupAlias(\"time\",$__interval),\n  avg(fsc_small) AS \"pro S\"\nFROM seaflow_geo\nWHERE\n  $__timeFilter(\"time\") AND\n  pop = 'synecho' AND\n  \"time\" >= '$turnaround'\nGROUP BY 1\nORDER BY 1",
          "refId": "C",
          "select": [
            [
              {
                "params": [
                  "fsc_small"
                ],
                "type": "column"
              },
              {
                "params": [
                  "avg"
                ],
                "type": "aggregate"
              },
              {
                "params": [
                  "pro S"
                ],
                "type": "alias"
              }
            ]
          ],
          "table": "seaflow_geo",
          "timeColumn": "\"time\"",
          "timeColumnType": "timestamptz",
          "where": [
            {
              "name": "$__timeFilter",
              "params": [],
              "type": "macro"
            },
            {
              "datatype": "text",
              "name": "",
              "params": [
                "pop",
                "=",
                "'synecho'"
              ],
              "type": "expression"
            },
            {
              "datatype": "timestamptz",
              "name": "",
              "params": [
                "\"time\"",
                ">=",
                "'$turnaround'"
              ],
              "type": "expression"
            }
          ]
        }
      ],
      "timeFrom": null,
      "timeShift": null,
      "title": "Synechococcus Forward Scatter",
      "type": "armbrustlab-2dscatter-panel",
      "xaxis": {
        "show": true
      },
      "yaxes": [
        {
          "format": "short",
          "logBase": 1,
          "max": null,
          "show": true
        }
      ]
    },
    {
      "datasource": "Gradients2",
      "fill": 0,
      "gridPos": {
        "h": 8,
        "w": 10,
        "x": 0,
        "y": 24
      },
      "id": 36,
      "lines": false,
      "linewidth": 1,
      "links": [],
      "pointradius": 1,
      "points": true,
      "range": {
        "from": null,
        "to": null
      },
      "targets": [
        {
          "format": "time_series",
          "group": [
            {
              "params": [
                "$__interval",
                "none"
              ],
              "type": "time"
            }
          ],
          "metricColumn": "none",
          "rawQuery": false,
          "rawSql": "SELECT\n  $__timeGroupAlias(\"time\",$__interval),\n  avg(lat) AS \"lat\"\nFROM seaflow_geo\nWHERE\n  $__timeFilter(\"time\") AND\n  pop = 'picoeuk'\nGROUP BY 1\nORDER BY 1",
          "refId": "A",
          "select": [
            [
              {
                "params": [
                  "lat"
                ],
                "type": "column"
              },
              {
                "params": [
                  "avg"
                ],
                "type": "aggregate"
              },
              {
                "params": [
                  "lat"
                ],
                "type": "alias"
              }
            ]
          ],
          "table": "seaflow_geo",
          "timeColumn": "\"time\"",
          "timeColumnType": "timestamptz",
          "where": [
            {
              "name": "$__timeFilter",
              "params": [],
              "type": "macro"
            },
            {
              "datatype": "text",
              "name": "",
              "params": [
                "pop",
                "=",
                "'picoeuk'"
              ],
              "type": "expression"
            }
          ]
        },
        {
          "format": "time_series",
          "group": [
            {
              "params": [
                "$__interval",
                "none"
              ],
              "type": "time"
            }
          ],
          "metricColumn": "none",
          "rawQuery": false,
          "rawSql": "SELECT\n  $__timeGroupAlias(\"time\",$__interval),\n  avg(abundance) AS \"pico N\"\nFROM seaflow_geo\nWHERE\n  $__timeFilter(\"time\") AND\n  pop = 'picoeuk' AND\n  \"time\" <= '$turnaround'\nGROUP BY 1\nORDER BY 1",
          "refId": "B",
          "select": [
            [
              {
                "params": [
                  "abundance"
                ],
                "type": "column"
              },
              {
                "params": [
                  "avg"
                ],
                "type": "aggregate"
              },
              {
                "params": [
                  "pico N"
                ],
                "type": "alias"
              }
            ]
          ],
          "table": "seaflow_geo",
          "timeColumn": "\"time\"",
          "timeColumnType": "timestamptz",
          "where": [
            {
              "name": "$__timeFilter",
              "params": [],
              "type": "macro"
            },
            {
              "datatype": "text",
              "name": "",
              "params": [
                "pop",
                "=",
                "'picoeuk'"
              ],
              "type": "expression"
            },
            {
              "datatype": "timestamptz",
              "name": "",
              "params": [
                "\"time\"",
                "<=",
                "'$turnaround'"
              ],
              "type": "expression"
            }
          ]
        },
        {
          "format": "time_series",
          "group": [
            {
              "params": [
                "$__interval",
                "none"
              ],
              "type": "time"
            }
          ],
          "metricColumn": "none",
          "rawQuery": false,
          "rawSql": "SELECT\n  $__timeGroupAlias(\"time\",$__interval),\n  avg(abundance) AS \"pico S\"\nFROM seaflow_geo\nWHERE\n  $__timeFilter(\"time\") AND\n  pop = 'picoeuk' AND\n  \"time\" >= '$turnaround'\nGROUP BY 1\nORDER BY 1",
          "refId": "C",
          "select": [
            [
              {
                "params": [
                  "abundance"
                ],
                "type": "column"
              },
              {
                "params": [
                  "avg"
                ],
                "type": "aggregate"
              },
              {
                "params": [
                  "pico S"
                ],
                "type": "alias"
              }
            ]
          ],
          "table": "seaflow_geo",
          "timeColumn": "\"time\"",
          "timeColumnType": "timestamptz",
          "where": [
            {
              "name": "$__timeFilter",
              "params": [],
              "type": "macro"
            },
            {
              "datatype": "text",
              "name": "",
              "params": [
                "pop",
                "=",
                "'picoeuk'"
              ],
              "type": "expression"
            },
            {
              "datatype": "timestamptz",
              "name": "",
              "params": [
                "\"time\"",
                ">=",
                "'$turnaround'"
              ],
              "type": "expression"
            }
          ]
        }
      ],
      "timeFrom": null,
      "timeShift": null,
      "title": "Picoeukaryotes Abundance",
      "type": "armbrustlab-2dscatter-panel",
      "xaxis": {
        "show": true
      },
      "yaxes": [
        {
          "format": "short",
          "logBase": 1,
          "max": null,
          "show": true
        }
      ]
    },
    {
      "datasource": "Gradients2",
      "fill": 0,
      "gridPos": {
        "h": 8,
        "w": 10,
        "x": 10,
        "y": 24
      },
      "id": 38,
      "lines": false,
      "linewidth": 1,
      "links": [],
      "pointradius": 1,
      "points": true,
      "range": {
        "from": null,
        "to": null
      },
      "targets": [
        {
          "format": "time_series",
          "group": [
            {
              "params": [
                "$__interval",
                "none"
              ],
              "type": "time"
            }
          ],
          "metricColumn": "none",
          "rawQuery": false,
          "rawSql": "SELECT\n  $__timeGroupAlias(\"time\",$__interval),\n  avg(lat) AS \"lat\"\nFROM seaflow_geo\nWHERE\n  $__timeFilter(\"time\") AND\n  pop = 'picoeuk'\nGROUP BY 1\nORDER BY 1",
          "refId": "A",
          "select": [
            [
              {
                "params": [
                  "lat"
                ],
                "type": "column"
              },
              {
                "params": [
                  "avg"
                ],
                "type": "aggregate"
              },
              {
                "params": [
                  "lat"
                ],
                "type": "alias"
              }
            ]
          ],
          "table": "seaflow_geo",
          "timeColumn": "\"time\"",
          "timeColumnType": "timestamptz",
          "where": [
            {
              "name": "$__timeFilter",
              "params": [],
              "type": "macro"
            },
            {
              "datatype": "text",
              "name": "",
              "params": [
                "pop",
                "=",
                "'picoeuk'"
              ],
              "type": "expression"
            }
          ]
        },
        {
          "format": "time_series",
          "group": [
            {
              "params": [
                "$__interval",
                "none"
              ],
              "type": "time"
            }
          ],
          "metricColumn": "none",
          "rawQuery": false,
          "rawSql": "SELECT\n  $__timeGroupAlias(\"time\",$__interval),\n  avg(fsc_small) AS \"pico N\"\nFROM seaflow_geo\nWHERE\n  $__timeFilter(\"time\") AND\n  pop = 'picoeuk' AND\n  \"time\" <= '$turnaround'\nGROUP BY 1\nORDER BY 1",
          "refId": "B",
          "select": [
            [
              {
                "params": [
                  "fsc_small"
                ],
                "type": "column"
              },
              {
                "params": [
                  "avg"
                ],
                "type": "aggregate"
              },
              {
                "params": [
                  "pico N"
                ],
                "type": "alias"
              }
            ]
          ],
          "table": "seaflow_geo",
          "timeColumn": "\"time\"",
          "timeColumnType": "timestamptz",
          "where": [
            {
              "name": "$__timeFilter",
              "params": [],
              "type": "macro"
            },
            {
              "datatype": "text",
              "name": "",
              "params": [
                "pop",
                "=",
                "'picoeuk'"
              ],
              "type": "expression"
            },
            {
              "datatype": "timestamptz",
              "name": "",
              "params": [
                "\"time\"",
                "<=",
                "'$turnaround'"
              ],
              "type": "expression"
            }
          ]
        },
        {
          "format": "time_series",
          "group": [
            {
              "params": [
                "$__interval",
                "none"
              ],
              "type": "time"
            }
          ],
          "metricColumn": "none",
          "rawQuery": false,
          "rawSql": "SELECT\n  $__timeGroupAlias(\"time\",$__interval),\n  avg(fsc_small) AS \"pico S\"\nFROM seaflow_geo\nWHERE\n  $__timeFilter(\"time\") AND\n  pop = 'picoeuk' AND\n  \"time\" >= '$turnaround'\nGROUP BY 1\nORDER BY 1",
          "refId": "C",
          "select": [
            [
              {
                "params": [
                  "fsc_small"
                ],
                "type": "column"
              },
              {
                "params": [
                  "avg"
                ],
                "type": "aggregate"
              },
              {
                "params": [
                  "pico S"
                ],
                "type": "alias"
              }
            ]
          ],
          "table": "seaflow_geo",
          "timeColumn": "\"time\"",
          "timeColumnType": "timestamptz",
          "where": [
            {
              "name": "$__timeFilter",
              "params": [],
              "type": "macro"
            },
            {
              "datatype": "text",
              "name": "",
              "params": [
                "pop",
                "=",
                "'picoeuk'"
              ],
              "type": "expression"
            },
            {
              "datatype": "timestamptz",
              "name": "",
              "params": [
                "\"time\"",
                ">=",
                "'$turnaround'"
              ],
              "type": "expression"
            }
          ]
        }
      ],
      "timeFrom": null,
      "timeShift": null,
      "title": "Picoeukaryotes Forward Scatter",
      "type": "armbrustlab-2dscatter-panel",
      "xaxis": {
        "show": true
      },
      "yaxes": [
        {
          "format": "short",
          "logBase": 1,
          "max": null,
          "show": true
        }
      ]
    },
    {
      "datasource": "Gradients2",
      "fill": 0,
      "gridPos": {
        "h": 8,
        "w": 7,
        "x": 0,
        "y": 32
      },
      "id": 20,
      "lines": false,
      "linewidth": 1,
      "links": [],
      "pointradius": 1,
      "points": true,
      "range": {
        "from": null,
        "to": null
      },
      "targets": [
        {
          "format": "time_series",
          "group": [
            {
              "params": [
                "$__interval",
                "none"
              ],
              "type": "time"
            }
          ],
          "metricColumn": "none",
          "rawQuery": false,
          "rawSql": "SELECT\n  $__timeGroupAlias(\"time\",$__interval),\n  avg(lat) AS \"lat\"\nFROM eco_geo\nWHERE\n  $__timeFilter(\"time\")\nGROUP BY 1\nORDER BY 1",
          "refId": "A",
          "select": [
            [
              {
                "params": [
                  "lat"
                ],
                "type": "column"
              },
              {
                "params": [
                  "avg"
                ],
                "type": "aggregate"
              },
              {
                "params": [
                  "lat"
                ],
                "type": "alias"
              }
            ]
          ],
          "table": "eco_geo",
          "timeColumn": "\"time\"",
          "timeColumnType": "timestamptz",
          "where": [
            {
              "name": "$__timeFilter",
              "params": [],
              "type": "macro"
            }
          ]
        },
        {
          "format": "time_series",
          "group": [
            {
              "params": [
                "$__interval",
                "none"
              ],
              "type": "time"
            }
          ],
          "metricColumn": "none",
          "rawQuery": false,
          "rawSql": "SELECT\n  $__timeGroupAlias(\"time\",$__interval),\n  avg(chl) AS \"chl\"\nFROM eco_geo\nWHERE\n  $__timeFilter(\"time\")\nGROUP BY 1\nORDER BY 1",
          "refId": "B",
          "select": [
            [
              {
                "params": [
                  "chl"
                ],
                "type": "column"
              },
              {
                "params": [
                  "avg"
                ],
                "type": "aggregate"
              },
              {
                "params": [
                  "chl"
                ],
                "type": "alias"
              }
            ]
          ],
          "table": "eco_geo",
          "timeColumn": "\"time\"",
          "timeColumnType": "timestamptz",
          "where": [
            {
              "name": "$__timeFilter",
              "params": [],
              "type": "macro"
            }
          ]
        },
        {
          "format": "time_series",
          "group": [
            {
              "params": [
                "$__interval",
                "none"
              ],
              "type": "time"
            }
          ],
          "metricColumn": "none",
          "rawQuery": false,
          "rawSql": "SELECT\n  $__timeGroupAlias(\"time\",$__interval),\n  avg(chl) AS \"chl2\"\nFROM eco_geo\nWHERE\n  $__timeFilter(\"time\") AND\n  \"time\" > '$turnaround'\nGROUP BY 1\nORDER BY 1",
          "refId": "C",
          "select": [
            [
              {
                "params": [
                  "chl"
                ],
                "type": "column"
              },
              {
                "params": [
                  "avg"
                ],
                "type": "aggregate"
              },
              {
                "params": [
                  "chl2"
                ],
                "type": "alias"
              }
            ]
          ],
          "table": "eco_geo",
          "timeColumn": "\"time\"",
          "timeColumnType": "timestamptz",
          "where": [
            {
              "name": "$__timeFilter",
              "params": [],
              "type": "macro"
            },
            {
              "datatype": "timestamptz",
              "name": "",
              "params": [
                "\"time\"",
                ">",
                "'$turnaround'"
              ],
              "type": "expression"
            }
          ]
        }
      ],
      "timeFrom": null,
      "timeShift": null,
      "title": "ECO chl",
      "type": "armbrustlab-2dscatter-panel",
      "xaxis": {
        "show": true
      },
      "yaxes": [
        {
          "format": "short",
          "logBase": 1,
          "show": true
        }
      ]
    },
    {
      "datasource": "Gradients2",
      "fill": 0,
      "gridPos": {
        "h": 8,
        "w": 6,
        "x": 7,
        "y": 32
      },
      "id": 22,
      "lines": false,
      "linewidth": 2,
      "links": [],
      "pointradius": 1,
      "points": true,
      "range": {
        "from": null,
        "to": null
      },
      "targets": [
        {
          "format": "time_series",
          "group": [
            {
              "params": [
                "$__interval",
                "none"
              ],
              "type": "time"
            }
          ],
          "metricColumn": "none",
          "rawQuery": false,
          "rawSql": "SELECT\n  $__timeGroupAlias(\"time\",$__interval),\n  avg(lat) AS \"lat\"\nFROM eco_geo\nWHERE\n  $__timeFilter(\"time\")\nGROUP BY 1\nORDER BY 1",
          "refId": "A",
          "select": [
            [
              {
                "params": [
                  "lat"
                ],
                "type": "column"
              },
              {
                "params": [
                  "avg"
                ],
                "type": "aggregate"
              },
              {
                "params": [
                  "lat"
                ],
                "type": "alias"
              }
            ]
          ],
          "table": "eco_geo",
          "timeColumn": "\"time\"",
          "timeColumnType": "timestamptz",
          "where": [
            {
              "name": "$__timeFilter",
              "params": [],
              "type": "macro"
            }
          ]
        },
        {
          "format": "time_series",
          "group": [
            {
              "params": [
                "$__interval",
                "none"
              ],
              "type": "time"
            }
          ],
          "metricColumn": "none",
          "rawQuery": false,
          "rawSql": "SELECT\n  $__timeGroupAlias(\"time\",$__interval),\n  avg(cdom) AS \"cdom N\"\nFROM eco_geo\nWHERE\n  $__timeFilter(\"time\") AND\n  \"time\" <= '$turnaround'\nGROUP BY 1\nORDER BY 1",
          "refId": "B",
          "select": [
            [
              {
                "params": [
                  "cdom"
                ],
                "type": "column"
              },
              {
                "params": [
                  "avg"
                ],
                "type": "aggregate"
              },
              {
                "params": [
                  "cdom N"
                ],
                "type": "alias"
              }
            ]
          ],
          "table": "eco_geo",
          "timeColumn": "\"time\"",
          "timeColumnType": "timestamptz",
          "where": [
            {
              "name": "$__timeFilter",
              "params": [],
              "type": "macro"
            },
            {
              "datatype": "timestamptz",
              "name": "",
              "params": [
                "\"time\"",
                "<=",
                "'$turnaround'"
              ],
              "type": "expression"
            }
          ]
        },
        {
          "format": "time_series",
          "group": [
            {
              "params": [
                "$__interval",
                "none"
              ],
              "type": "time"
            }
          ],
          "metricColumn": "none",
          "rawQuery": false,
          "rawSql": "SELECT\n  $__timeGroupAlias(\"time\",$__interval),\n  avg(cdom) AS \"cdom S\"\nFROM eco_geo\nWHERE\n  $__timeFilter(\"time\") AND\n  \"time\" >= '$turnaround'\nGROUP BY 1\nORDER BY 1",
          "refId": "C",
          "select": [
            [
              {
                "params": [
                  "cdom"
                ],
                "type": "column"
              },
              {
                "params": [
                  "avg"
                ],
                "type": "aggregate"
              },
              {
                "params": [
                  "cdom S"
                ],
                "type": "alias"
              }
            ]
          ],
          "table": "eco_geo",
          "timeColumn": "\"time\"",
          "timeColumnType": "timestamptz",
          "where": [
            {
              "name": "$__timeFilter",
              "params": [],
              "type": "macro"
            },
            {
              "datatype": "timestamptz",
              "name": "",
              "params": [
                "\"time\"",
                ">=",
                "'$turnaround'"
              ],
              "type": "expression"
            }
          ]
        }
      ],
      "timeFrom": null,
      "timeShift": null,
      "title": "ECO CDOM",
      "type": "armbrustlab-2dscatter-panel",
      "xaxis": {
        "show": true
      },
      "yaxes": [
        {
          "format": "short",
          "logBase": 1,
          "show": true
        }
      ]
    },
    {
      "datasource": "Gradients2",
      "fill": 0,
      "gridPos": {
        "h": 8,
        "w": 7,
        "x": 13,
        "y": 32
      },
      "id": 24,
      "lines": true,
      "linewidth": 0,
      "links": [],
      "pointradius": 1,
      "points": true,
      "range": {
        "from": null,
        "to": null
      },
      "targets": [
        {
          "format": "time_series",
          "group": [
            {
              "params": [
                "$__interval",
                "none"
              ],
              "type": "time"
            }
          ],
          "metricColumn": "none",
          "rawQuery": false,
          "rawSql": "SELECT\n  $__timeGroupAlias(\"time\",$__interval),\n  avg(lat) AS \"lat\"\nFROM eco_geo\nWHERE\n  $__timeFilter(\"time\")\nGROUP BY 1\nORDER BY 1",
          "refId": "A",
          "select": [
            [
              {
                "params": [
                  "lat"
                ],
                "type": "column"
              },
              {
                "params": [
                  "avg"
                ],
                "type": "aggregate"
              },
              {
                "params": [
                  "lat"
                ],
                "type": "alias"
              }
            ]
          ],
          "table": "eco_geo",
          "timeColumn": "\"time\"",
          "timeColumnType": "timestamptz",
          "where": [
            {
              "name": "$__timeFilter",
              "params": [],
              "type": "macro"
            }
          ]
        },
        {
          "format": "time_series",
          "group": [
            {
              "params": [
                "$__interval",
                "none"
              ],
              "type": "time"
            }
          ],
          "metricColumn": "none",
          "rawQuery": false,
          "rawSql": "SELECT\n  $__timeGroupAlias(\"time\",$__interval),\n  avg(scattering) AS \"scattering N\"\nFROM eco_geo\nWHERE\n  $__timeFilter(\"time\") AND\n  \"time\" <= '$turnaround'\nGROUP BY 1\nORDER BY 1",
          "refId": "B",
          "select": [
            [
              {
                "params": [
                  "scattering"
                ],
                "type": "column"
              },
              {
                "params": [
                  "avg"
                ],
                "type": "aggregate"
              },
              {
                "params": [
                  "scattering N"
                ],
                "type": "alias"
              }
            ]
          ],
          "table": "eco_geo",
          "timeColumn": "\"time\"",
          "timeColumnType": "timestamptz",
          "where": [
            {
              "name": "$__timeFilter",
              "params": [],
              "type": "macro"
            },
            {
              "datatype": "timestamptz",
              "name": "",
              "params": [
                "\"time\"",
                "<=",
                "'$turnaround'"
              ],
              "type": "expression"
            }
          ]
        },
        {
          "format": "time_series",
          "group": [
            {
              "params": [
                "$__interval",
                "none"
              ],
              "type": "time"
            }
          ],
          "metricColumn": "none",
          "rawQuery": false,
          "rawSql": "SELECT\n  $__timeGroupAlias(\"time\",$__interval),\n  avg(scattering) AS \"scattering S\"\nFROM eco_geo\nWHERE\n  $__timeFilter(\"time\") AND\n  \"time\" >= '$turnaround'\nGROUP BY 1\nORDER BY 1",
          "refId": "C",
          "select": [
            [
              {
                "params": [
                  "scattering"
                ],
                "type": "column"
              },
              {
                "params": [
                  "avg"
                ],
                "type": "aggregate"
              },
              {
                "params": [
                  "scattering S"
                ],
                "type": "alias"
              }
            ]
          ],
          "table": "eco_geo",
          "timeColumn": "\"time\"",
          "timeColumnType": "timestamptz",
          "where": [
            {
              "name": "$__timeFilter",
              "params": [],
              "type": "macro"
            },
            {
              "datatype": "timestamptz",
              "name": "",
              "params": [
                "\"time\"",
                ">=",
                "'$turnaround'"
              ],
              "type": "expression"
            }
          ]
        }
      ],
      "timeFrom": null,
      "timeShift": null,
      "title": "ECO Scattering",
      "type": "armbrustlab-2dscatter-panel",
      "xaxis": {
        "show": true
      },
      "yaxes": [
        {
          "format": "short",
          "logBase": 1,
          "show": true
        }
      ]
    },
    {
      "datasource": "Gradients2",
      "fill": 1,
      "gridPos": {
        "h": 8,
        "w": 7,
        "x": 0,
        "y": 40
      },
      "id": 26,
      "lines": false,
      "linewidth": 1,
      "links": [],
      "pointradius": 1,
      "points": true,
      "range": {
        "from": null,
        "to": null
      },
      "targets": [
        {
          "format": "time_series",
          "group": [
            {
              "params": [
                "$__interval",
                "none"
              ],
              "type": "time"
            }
          ],
          "metricColumn": "none",
          "rawQuery": false,
          "rawSql": "SELECT\n  $__timeGroupAlias(\"time\",$__interval),\n  avg(lat) AS \"lat\"\nFROM acs_geo\nWHERE\n  $__timeFilter(\"time\")\nGROUP BY 1\nORDER BY 1",
          "refId": "A",
          "select": [
            [
              {
                "params": [
                  "lat"
                ],
                "type": "column"
              },
              {
                "params": [
                  "avg"
                ],
                "type": "aggregate"
              },
              {
                "params": [
                  "lat"
                ],
                "type": "alias"
              }
            ]
          ],
          "table": "acs_geo",
          "timeColumn": "\"time\"",
          "timeColumnType": "timestamptz",
          "where": [
            {
              "name": "$__timeFilter",
              "params": [],
              "type": "macro"
            }
          ]
        },
        {
          "format": "time_series",
          "group": [
            {
              "params": [
                "$__interval",
                "none"
              ],
              "type": "time"
            }
          ],
          "metricColumn": "none",
          "rawQuery": false,
          "rawSql": "SELECT\n  $__timeGroupAlias(\"time\",$__interval),\n  avg(chl) AS \"chl N\"\nFROM acs_geo\nWHERE\n  $__timeFilter(\"time\") AND\n  \"time\" <= '$turnaround'\nGROUP BY 1\nORDER BY 1",
          "refId": "B",
          "select": [
            [
              {
                "params": [
                  "chl"
                ],
                "type": "column"
              },
              {
                "params": [
                  "avg"
                ],
                "type": "aggregate"
              },
              {
                "params": [
                  "chl N"
                ],
                "type": "alias"
              }
            ]
          ],
          "table": "acs_geo",
          "timeColumn": "\"time\"",
          "timeColumnType": "timestamptz",
          "where": [
            {
              "name": "$__timeFilter",
              "params": [],
              "type": "macro"
            },
            {
              "datatype": "timestamptz",
              "name": "",
              "params": [
                "\"time\"",
                "<=",
                "'$turnaround'"
              ],
              "type": "expression"
            }
          ]
        },
        {
          "format": "time_series",
          "group": [
            {
              "params": [
                "$__interval",
                "none"
              ],
              "type": "time"
            }
          ],
          "metricColumn": "none",
          "rawQuery": false,
          "rawSql": "SELECT\n  $__timeGroupAlias(\"time\",$__interval),\n  avg(chl) AS \"chl S\"\nFROM acs_geo\nWHERE\n  $__timeFilter(\"time\") AND\n  \"time\" >= '$turnaround'\nGROUP BY 1\nORDER BY 1",
          "refId": "C",
          "select": [
            [
              {
                "params": [
                  "chl"
                ],
                "type": "column"
              },
              {
                "params": [
                  "avg"
                ],
                "type": "aggregate"
              },
              {
                "params": [
                  "chl S"
                ],
                "type": "alias"
              }
            ]
          ],
          "table": "acs_geo",
          "timeColumn": "\"time\"",
          "timeColumnType": "timestamptz",
          "where": [
            {
              "name": "$__timeFilter",
              "params": [],
              "type": "macro"
            },
            {
              "datatype": "timestamptz",
              "name": "",
              "params": [
                "\"time\"",
                ">=",
                "'$turnaround'"
              ],
              "type": "expression"
            }
          ]
        }
      ],
      "timeFrom": null,
      "timeShift": null,
      "title": "ACS Chl",
      "type": "armbrustlab-2dscatter-panel",
      "xaxis": {
        "show": true
      },
      "yaxes": [
        {
          "format": "short",
          "logBase": 1,
          "show": true
        }
      ]
    },
    {
      "datasource": "Gradients2",
      "fill": 0,
      "gridPos": {
        "h": 8,
        "w": 6,
        "x": 7,
        "y": 40
      },
      "id": 28,
      "lines": false,
      "linewidth": 1,
      "links": [],
      "pointradius": 1,
      "points": true,
      "range": {
        "from": null,
        "to": null
      },
      "targets": [
        {
          "format": "time_series",
          "group": [
            {
              "params": [
                "$__interval",
                "none"
              ],
              "type": "time"
            }
          ],
          "metricColumn": "none",
          "rawQuery": false,
          "rawSql": "SELECT\n  $__timeGroupAlias(\"time\",$__interval),\n  avg(lat) AS \"lat\"\nFROM acs_geo\nWHERE\n  $__timeFilter(\"time\")\nGROUP BY 1\nORDER BY 1",
          "refId": "A",
          "select": [
            [
              {
                "params": [
                  "lat"
                ],
                "type": "column"
              },
              {
                "params": [
                  "avg"
                ],
                "type": "aggregate"
              },
              {
                "params": [
                  "lat"
                ],
                "type": "alias"
              }
            ]
          ],
          "table": "acs_geo",
          "timeColumn": "\"time\"",
          "timeColumnType": "timestamptz",
          "where": [
            {
              "name": "$__timeFilter",
              "params": [],
              "type": "macro"
            }
          ]
        },
        {
          "format": "time_series",
          "group": [
            {
              "params": [
                "$__interval",
                "none"
              ],
              "type": "time"
            }
          ],
          "metricColumn": "none",
          "rawQuery": false,
          "rawSql": "SELECT\n  $__timeGroupAlias(\"time\",$__interval),\n  avg(cp650) AS \"cp650 N\"\nFROM acs_geo\nWHERE\n  $__timeFilter(\"time\") AND\n  \"time\" <= '$turnaround'\nGROUP BY 1\nORDER BY 1",
          "refId": "B",
          "select": [
            [
              {
                "params": [
                  "cp650"
                ],
                "type": "column"
              },
              {
                "params": [
                  "avg"
                ],
                "type": "aggregate"
              },
              {
                "params": [
                  "cp650 N"
                ],
                "type": "alias"
              }
            ]
          ],
          "table": "acs_geo",
          "timeColumn": "\"time\"",
          "timeColumnType": "timestamptz",
          "where": [
            {
              "name": "$__timeFilter",
              "params": [],
              "type": "macro"
            },
            {
              "datatype": "timestamptz",
              "name": "",
              "params": [
                "\"time\"",
                "<=",
                "'$turnaround'"
              ],
              "type": "expression"
            }
          ]
        },
        {
          "format": "time_series",
          "group": [
            {
              "params": [
                "$__interval",
                "none"
              ],
              "type": "time"
            }
          ],
          "metricColumn": "none",
          "rawQuery": false,
          "rawSql": "SELECT\n  $__timeGroupAlias(\"time\",$__interval),\n  avg(cp650) AS \"cp650 S\"\nFROM acs_geo\nWHERE\n  $__timeFilter(\"time\") AND\n  \"time\" >= '$turnaround'\nGROUP BY 1\nORDER BY 1",
          "refId": "C",
          "select": [
            [
              {
                "params": [
                  "cp650"
                ],
                "type": "column"
              },
              {
                "params": [
                  "avg"
                ],
                "type": "aggregate"
              },
              {
                "params": [
                  "cp650 S"
                ],
                "type": "alias"
              }
            ]
          ],
          "table": "acs_geo",
          "timeColumn": "\"time\"",
          "timeColumnType": "timestamptz",
          "where": [
            {
              "name": "$__timeFilter",
              "params": [],
              "type": "macro"
            },
            {
              "datatype": "timestamptz",
              "name": "",
              "params": [
                "\"time\"",
                ">=",
                "'$turnaround'"
              ],
              "type": "expression"
            }
          ]
        }
      ],
      "timeFrom": null,
      "timeShift": null,
      "title": "ACS cp650",
      "type": "armbrustlab-2dscatter-panel",
      "xaxis": {
        "show": true
      },
      "yaxes": [
        {
          "format": "short",
          "logBase": 1,
          "show": true
        }
      ]
    },
    {
      "datasource": "Gradients2",
      "fill": 0,
      "gridPos": {
        "h": 8,
        "w": 7,
        "x": 13,
        "y": 40
      },
      "id": 30,
      "lines": false,
      "linewidth": 1,
      "links": [],
      "pointradius": 1,
      "points": true,
      "range": {
        "from": null,
        "to": null
      },
      "targets": [
        {
          "format": "time_series",
          "group": [
            {
              "params": [
                "$__interval",
                "none"
              ],
              "type": "time"
            }
          ],
          "metricColumn": "none",
          "rawQuery": false,
          "rawSql": "SELECT\n  $__timeGroupAlias(\"time\",$__interval),\n  avg(lat) AS \"lat\"\nFROM po4_geo\nWHERE\n  $__timeFilter(\"time\")\nGROUP BY 1\nORDER BY 1",
          "refId": "A",
          "select": [
            [
              {
                "params": [
                  "lat"
                ],
                "type": "column"
              },
              {
                "params": [
                  "avg"
                ],
                "type": "aggregate"
              },
              {
                "params": [
                  "lat"
                ],
                "type": "alias"
              }
            ]
          ],
          "table": "po4_geo",
          "timeColumn": "\"time\"",
          "timeColumnType": "timestamptz",
          "where": [
            {
              "name": "$__timeFilter",
              "params": [],
              "type": "macro"
            }
          ]
        },
        {
          "format": "time_series",
          "group": [
            {
              "params": [
                "$__interval",
                "none"
              ],
              "type": "time"
            }
          ],
          "metricColumn": "none",
          "rawQuery": false,
          "rawSql": "SELECT\n  $__timeGroupAlias(\"time\",$__interval),\n  avg(po4) AS \"po4 N\"\nFROM po4_geo\nWHERE\n  $__timeFilter(\"time\") AND\n  \"time\" <= '$turnaround'\nGROUP BY 1\nORDER BY 1",
          "refId": "B",
          "select": [
            [
              {
                "params": [
                  "po4"
                ],
                "type": "column"
              },
              {
                "params": [
                  "avg"
                ],
                "type": "aggregate"
              },
              {
                "params": [
                  "po4 N"
                ],
                "type": "alias"
              }
            ]
          ],
          "table": "po4_geo",
          "timeColumn": "\"time\"",
          "timeColumnType": "timestamptz",
          "where": [
            {
              "name": "$__timeFilter",
              "params": [],
              "type": "macro"
            },
            {
              "datatype": "timestamptz",
              "name": "",
              "params": [
                "\"time\"",
                "<=",
                "'$turnaround'"
              ],
              "type": "expression"
            }
          ]
        },
        {
          "format": "time_series",
          "group": [
            {
              "params": [
                "$__interval",
                "none"
              ],
              "type": "time"
            }
          ],
          "metricColumn": "none",
          "rawQuery": false,
          "rawSql": "SELECT\n  $__timeGroupAlias(\"time\",$__interval),\n  avg(po4) AS \"po4 S\"\nFROM po4_geo\nWHERE\n  $__timeFilter(\"time\") AND\n  \"time\" >= '$turnaround'\nGROUP BY 1\nORDER BY 1",
          "refId": "C",
          "select": [
            [
              {
                "params": [
                  "po4"
                ],
                "type": "column"
              },
              {
                "params": [
                  "avg"
                ],
                "type": "aggregate"
              },
              {
                "params": [
                  "po4 S"
                ],
                "type": "alias"
              }
            ]
          ],
          "table": "po4_geo",
          "timeColumn": "\"time\"",
          "timeColumnType": "timestamptz",
          "where": [
            {
              "name": "$__timeFilter",
              "params": [],
              "type": "macro"
            },
            {
              "datatype": "timestamptz",
              "name": "",
              "params": [
                "\"time\"",
                ">=",
                "'$turnaround'"
              ],
              "type": "expression"
            }
          ]
        }
      ],
      "timeFrom": null,
      "timeShift": null,
      "title": "PO4",
      "type": "armbrustlab-2dscatter-panel",
      "xaxis": {
        "show": true
      },
      "yaxes": [
        {
          "format": "short",
          "logBase": 1,
          "show": true
        }
      ]
    }
  ],
  "refresh": false,
  "schemaVersion": 18,
  "style": "dark",
  "tags": [],
  "templating": {
    "list": [
      {
        "allValue": null,
        "current": {
          "tags": [],
          "text": "2017-06-02T23:30:00Z",
          "value": "2017-06-02T23:30:00Z"
        },
        "hide": 0,
        "includeAll": false,
        "label": "Timestamp of North/South track change",
        "multi": false,
        "name": "turnaround",
        "options": [
          {
            "selected": true,
            "text": "2017-06-02T23:30:00Z",
            "value": "2017-06-02T23:30:00Z"
          }
        ],
        "query": "2017-06-02T23:30:00Z",
        "skipUrlSync": false,
        "type": "custom"
      }
    ]
  },
  "time": {
    "from": "2017-05-27T05:15:12.377Z",
    "to": "2017-06-14T20:24:02.070Z"
  },
  "timepicker": {
    "refresh_intervals": [
      "5s",
      "10s",
      "30s",
      "1m",
      "5m",
      "15m",
      "30m",
      "1h",
      "2h",
      "1d"
    ],
    "time_options": [
      "5m",
      "15m",
      "1h",
      "6h",
      "12h",
      "24h",
      "2d",
      "7d",
      "30d"
    ]
  },
  "timezone": "utc",
  "title": "Gradients2 By Latitude",
  "uid": "89vZ22rmk",
  "version": 10
}